soneti_tasks/CopyToFuseki.py
soneti_tasks/GSICrawlerScraper.py
soneti_tasks/SenpyAnalysis.py
soneti_tasks/__init__.py
soneti_tasks-0.0.3.dist-info/LICENSE
soneti_tasks-0.0.3.dist-info/METADATA
soneti_tasks-0.0.3.dist-info/WHEEL
soneti_tasks-0.0.3.dist-info/top_level.txt
soneti_tasks-0.0.3.dist-info/RECORD
