Metadata-Version: 2.1
Name: soneti-tasks
Version: 0.0.3
Summary: Luigi Tasks for Soneti Orchestration
Home-page: https://lab.cluster.gsi.dit.upm.es/social/orchestrator
Author: Alberto Pascual
Author-email: apascual93@gmail.com
License: UNKNOWN
Platform: UNKNOWN
Requires-Dist: luigi
